aoku/__init__.py
aoku/aoku.py
aoku-2.3.0.dist-info/METADATA
aoku-2.3.0.dist-info/WHEEL
aoku-2.3.0.dist-info/top_level.txt
aoku-2.3.0.dist-info/RECORD
