Metadata-Version: 2.1
Name: aoku
Version: 2.3.0
Summary: The package for writing your own discord bot
Home-page: https://aokuapi.herokuapp.com/
Author: AineD3V
Author-email: priskozena@gmail.com
License: UNKNOWN
Platform: UNKNOWN
Classifier: Programming Language :: Python :: 3.8
Classifier: License :: OSI Approved :: GNU General Public License (GPL)
Classifier: Operating System :: OS Independent
Requires-Python: >=3.6
Requires-Dist: disnake
Requires-Dist: disnake[voice]
Requires-Dist: youtube-dl
Requires-Dist: datetime
Requires-Dist: requests
